GulpZhongwenWendang/README.md
GulpZhongwenWendang/__init__.py
GulpZhongwenWendang/__main__.py
GulpZhongwenWendang/file.epub
GulpZhongwenWendang/index.html
GulpZhongwenWendang/css/__init__.py
GulpZhongwenWendang/css/annotations.css
GulpZhongwenWendang/css/main.css
GulpZhongwenWendang/css/normalize.css
GulpZhongwenWendang/css/popup.css
GulpZhongwenWendang/font/__init__.py
GulpZhongwenWendang/font/fontello.eot
GulpZhongwenWendang/font/fontello.svg
GulpZhongwenWendang/font/fontello.ttf
GulpZhongwenWendang/font/fontello.woff
GulpZhongwenWendang/img/__init__.py
GulpZhongwenWendang/img/annotator-glyph-sprite.png
GulpZhongwenWendang/img/annotator-icon-sprite.png
GulpZhongwenWendang/img/apple-touch-icon.png
GulpZhongwenWendang/img/cancelfullscreen.png
GulpZhongwenWendang/img/close.png
GulpZhongwenWendang/img/fullscreen.png
GulpZhongwenWendang/img/loader.gif
GulpZhongwenWendang/img/menu-icon.png
GulpZhongwenWendang/img/save.png
GulpZhongwenWendang/img/saved.png
GulpZhongwenWendang/img/settings-s.png
GulpZhongwenWendang/img/settings.png
GulpZhongwenWendang/img/star.png
GulpZhongwenWendang/js/__init__.py
GulpZhongwenWendang/js/epub.js
GulpZhongwenWendang/js/epub.min.js
GulpZhongwenWendang/js/epub.min.map
GulpZhongwenWendang/js/hooks.min.js
GulpZhongwenWendang/js/hooks.min.map
GulpZhongwenWendang/js/reader.js
GulpZhongwenWendang/js/reader.js.map
GulpZhongwenWendang/js/reader.min.js
GulpZhongwenWendang/js/reader.min.map
GulpZhongwenWendang/js/hooks/__init__.py
GulpZhongwenWendang/js/hooks/extensions/__init__.py
GulpZhongwenWendang/js/hooks/extensions/highlight.js
GulpZhongwenWendang/js/libs/__init__.py
GulpZhongwenWendang/js/libs/jquery.min.js
GulpZhongwenWendang/js/libs/localforage.min.js
GulpZhongwenWendang/js/libs/screenfull.js
GulpZhongwenWendang/js/libs/screenfull.min.js
GulpZhongwenWendang/js/libs/zip.min.js
GulpZhongwenWendang/js/plugins/__init__.py
GulpZhongwenWendang/js/plugins/hypothesis.js
GulpZhongwenWendang/js/plugins/search.js
gulp_zhongwen_wendang-2024.3.1.0.dist-info/METADATA
gulp_zhongwen_wendang-2024.3.1.0.dist-info/WHEEL
gulp_zhongwen_wendang-2024.3.1.0.dist-info/entry_points.txt
gulp_zhongwen_wendang-2024.3.1.0.dist-info/top_level.txt
gulp_zhongwen_wendang-2024.3.1.0.dist-info/RECORD
